odoo/addons/connector_elasticsearch/README.rst
odoo/addons/connector_elasticsearch/__init__.py
odoo/addons/connector_elasticsearch/__manifest__.py
odoo/addons/connector_elasticsearch/demo/backend_demo.xml
odoo/addons/connector_elasticsearch/i18n/connector_elasticsearch.pot
odoo/addons/connector_elasticsearch/i18n/it.po
odoo/addons/connector_elasticsearch/models/__init__.py
odoo/addons/connector_elasticsearch/models/se_backend.py
odoo/addons/connector_elasticsearch/models/se_index.py
odoo/addons/connector_elasticsearch/readme/CONTRIBUTORS.rst
odoo/addons/connector_elasticsearch/readme/DESCRIPTION.rst
odoo/addons/connector_elasticsearch/readme/HISTORY.rst
odoo/addons/connector_elasticsearch/static/description/icon.png
odoo/addons/connector_elasticsearch/static/description/index.html
odoo/addons/connector_elasticsearch/tests/__init__.py
odoo/addons/connector_elasticsearch/tests/docker-compose.elasticsearch.example.yml
odoo/addons/connector_elasticsearch/tests/test_connector_elasticsearch.py
odoo/addons/connector_elasticsearch/tests/cassettes/TestConnectorElasticsearch.test_each_with_corrupted_index.yaml
odoo/addons/connector_elasticsearch/tests/cassettes/TestConnectorElasticsearch.test_index_adapter_delete.yaml
odoo/addons/connector_elasticsearch/tests/cassettes/TestConnectorElasticsearch.test_index_adapter_delete_nonexisting_documents.yaml
odoo/addons/connector_elasticsearch/tests/cassettes/TestConnectorElasticsearch.test_index_adapter_index_and_iter.yaml
odoo/addons/connector_elasticsearch/tests/cassettes/TestConnectorElasticsearch.test_index_adapter_reindex.yaml
odoo/addons/connector_elasticsearch/tools/__init__.py
odoo/addons/connector_elasticsearch/tools/adapter.py
odoo/addons/connector_elasticsearch/views/se_backend.xml
odoo_addon_connector_elasticsearch-16.0.1.0.0.dist-info/METADATA
odoo_addon_connector_elasticsearch-16.0.1.0.0.dist-info/WHEEL
odoo_addon_connector_elasticsearch-16.0.1.0.0.dist-info/top_level.txt
odoo_addon_connector_elasticsearch-16.0.1.0.0.dist-info/RECORD
