Metadata-Version: 2.1
Name: odoo-addon-connector_elasticsearch
Version: 16.0.1.0.0
Summary: Connector For Elasticsearch Search Engine
Home-page: https://github.com/OCA/search-engine
Author: ACSONE SA/NV, Odoo Community Association (OCA)
Author-email: support@odoo-community.org
License: AGPL-3
Classifier: Programming Language :: Python
Classifier: Framework :: Odoo
Classifier: Framework :: Odoo :: 16.0
Classifier: License :: OSI Approved :: GNU Affero General Public License v3
Requires-Python: >=3.10
Requires-Dist: elasticsearch<=7.13.4,>=7.0.0
Requires-Dist: odoo-addon-connector-search-engine<16.1dev,>=16.0dev
Requires-Dist: odoo<16.1dev,>=16.0a
Requires-Dist: requests
